setup.py
src/__init__.py
src/ken_api.py
tbc_ken_api.egg-info/PKG-INFO
tbc_ken_api.egg-info/README.MD
tbc_ken_api.egg-info/SOURCES.txt
tbc_ken_api.egg-info/dependency_links.txt
tbc_ken_api.egg-info/not-zip-safe
tbc_ken_api.egg-info/requires.txt
tbc_ken_api.egg-info/top_level.txt