Metadata-Version: 2.1
Name: tbc-ken-api
Version: 0.3.8
Summary: Trading Bot Club alpaca api
Home-page: https://pypi.org/project/tbc-ken-api/
Author: Kris Luangpenthong
Author-email: krisken4699@gmail.com
License: UNKNOWN
Platform: UNKNOWN
Requires-Python: >=3.10
